phenofect/ChillDay.py
phenofect/Preprocessing.py
phenofect/Variables.py
phenofect/__init__.py
phenofect/Data/Japan/camellia_phenology_data.csv
phenofect/Data/Japan/cherry_phenology_data.csv
phenofect/Data/Japan/dandelion_phenology_data.csv
phenofect/Data/Japan/narcissus_phenology_data.csv
phenofect/Data/Japan/plumblossom_phenology_data.csv
phenofect/Data/Japan/wisteria_phenology_data.csv
phenofect/Data/Korea/OBS_phenology_data (autumn).csv
phenofect/Data/Korea/OBS_phenology_data.csv
phenofect/Data/Korea/azalea_phenology_data.csv
phenofect/Data/Korea/cherry_phenology_data.csv
phenofect/Data/Korea/daily_meteorological_data.csv
phenofect/Data/Korea/daylen_temperature_data.csv
phenofect/Data/Korea/forsythia_phenology_data.csv
phenofect/Data/Korea/monthly_meteorological_data.csv
phenofect-1.0.3.dist-info/LICENSE
phenofect-1.0.3.dist-info/METADATA
phenofect-1.0.3.dist-info/WHEEL
phenofect-1.0.3.dist-info/top_level.txt
phenofect-1.0.3.dist-info/RECORD
