Metadata-Version: 2.1
Name: phenofect
Version: 1.0.3
Summary: Package for Forecasting and Exploration of Plant Phenology under Climate Change, which has Parameter Examination, Visualization, Clustering and so on... with Phenological & Meteorological Data.
Home-page: https://github.com/SongWon03/PhenoFECT
Author: Songwon Kim
Author-email: kimsongwon10@korea.ac.kr
License: MIT
Classifier: Programming Language :: Python :: 3
Classifier: License :: OSI Approved :: MIT License
Classifier: Operating System :: OS Independent
Requires-Python: >=3.6
License-File: LICENSE
Requires-Dist: numpy
Requires-Dist: pandas
Requires-Dist: scikit-learn
Requires-Dist: matplotlib
Requires-Dist: seaborn
Requires-Dist: scipy
Requires-Dist: tqdm
Requires-Dist: requests
Requires-Dist: beautifulsoup4
